femio/__init__.py
femio/__main__/__init__.py
femio/__main__/femconvert.py
femio/config.py
femio/fem_attribute.py
femio/fem_attributes.py
femio/fem_data.py
femio/fem_elemental_attribute.py
femio/fem_writer.py
femio/formats/__init__.py
femio/formats/ensight/ensight.py
femio/formats/fistr/fistr.py
femio/formats/fistr/write_fistr.py
femio/formats/obj/obj.py
femio/formats/obj/write_obj.py
femio/formats/polyvtk/polyvtk.py
femio/formats/polyvtk/write_polyvtk.py
femio/formats/stl/stl.py
femio/formats/stl/write_stl.py
femio/formats/ucd/ucd.py
femio/formats/ucd/write_ucd.py
femio/formats/vtp/vtp.py
femio/formats/vtp/write_vtp.py
femio/functions.py
femio/geometry_processor.py
femio/graph_processor.py
femio/io.py
femio/mesh_compressor.py
femio/nodal_data.py
femio/signal_processor.py
femio/time_series_dataframe.py
femio/util/__init__.py
femio/util/brick_generator.py
femio/util/random_generator.py
femio/util/string_parser.py
femio-0.3.2.dist-info/entry_points.txt
femio-0.3.2.dist-info/LICENSE
femio-0.3.2.dist-info/WHEEL
femio-0.3.2.dist-info/METADATA
femio-0.3.2.dist-info/RECORD
