Metadata-Version: 2.1
Name: femio
Version: 0.3.2
Summary: FEM I/O Tool
Home-page: https://github.com/ricosjp/femio
Author: RICOS Co. Ltd.
Requires-Python: >=3.8,<3.10
Classifier: Programming Language :: Python :: 3
Classifier: Programming Language :: Python :: 3.8
Classifier: Programming Language :: Python :: 3.9
Provides-Extra: PyQt5
Requires-Dist: PyQt5 (>=5.14.0,<6.0.0); extra == "PyQt5"
Requires-Dist: kiwisolver (==1.0.1)
Requires-Dist: lxml (>=4.6.3,<5.0.0)
Requires-Dist: matplotlib (>=3.1,<4.0)
Requires-Dist: mayavi (>=4.7.3,<5.0.0)
Requires-Dist: meshio (>=3.3,<4.0)
Requires-Dist: networkx (>=2.4,<3.0)
Requires-Dist: numba (>=0.53.1,<0.54.0)
Requires-Dist: numpy (>=1.20,<2.0)
Requires-Dist: numpy-stl (>=2.13,<3.0)
Requires-Dist: pandas (>=1.0,<2.0)
Requires-Dist: scikit-learn (>=0.24.0,<0.25.0)
Requires-Dist: scipy (>=1.7.0,<2.0.0)
Requires-Dist: vtk (>=9.0.3,<10.0.0)
Project-URL: Documentation, https://ricosjp.github.io/femio/
Project-URL: Repository, https://github.com/ricosjp/femio
